MANIFEST.in
README.rst
balanced_ach.py
setup.py
balanced_ach.egg-info/PKG-INFO
balanced_ach.egg-info/SOURCES.txt
balanced_ach.egg-info/dependency_links.txt
balanced_ach.egg-info/requires.txt
balanced_ach.egg-info/top_level.txt