Metadata-Version: 1.0
Name: balanced-ach
Version: 0.1.3
Summary: Balanced ACH client library
Home-page: https://x.balancedpayments.com/a0
Author: Balanced
Author-email: dev@balancedpayments.com
License: BSD
Platform: UNKNOWN
Classifier: Intended Audience :: Developers
Classifier: License :: OSI Approved :: BSD License
Classifier: Programming Language :: Python
Classifier: Topic :: Software Development :: Libraries :: Python Modules
